{
	"configurations" : 
	[
		{
			"directories" : 
			[
				{
					"build" : ".",
					"jsonFile" : "directory-.-Debug-d0094a50bb2071803777.json",
					"minimumCMakeVersion" : 
					{
						"string" : "3.24"
					},
					"projectIndex" : 0,
					"source" : ".",
					"targetIndexes" : 
					[
						0
					]
				}
			],
			"name" : "Debug",
			"projects" : 
			[
				{
					"directoryIndexes" : 
					[
						0
					],
					"name" : "Big_Project_excel",
					"targetIndexes" : 
					[
						0
					]
				}
			],
			"targets" : 
			[
				{
					"directoryIndex" : 0,
					"id" : "Big_Project_excel::@6890427a1f51a3e7e1df",
					"jsonFile" : "target-Big_Project_excel-Debug-ab053f69444a239460ae.json",
					"name" : "Big_Project_excel",
					"projectIndex" : 0
				}
			]
		}
	],
	"kind" : "codemodel",
	"paths" : 
	{
		"build" : "C:/Users/annab/Big_Project_excel/cmake-build-debug",
		"source" : "C:/Users/annab/Big_Project_excel"
	},
	"version" : 
	{
		"major" : 2,
		"minor" : 4
	}
}
